can_remote/__init__.py
can_remote/__main__.py
can_remote/client.py
can_remote/protocol.py
can_remote/server.py
can_remote/version.py
can_remote/websocket.py
can_remote/web/index.html
can_remote/web/assets/bundle.js.gz
can_remote/web/assets/glyphicons-halflings-regular.eot
can_remote/web/assets/glyphicons-halflings-regular.svg
can_remote/web/assets/glyphicons-halflings-regular.ttf
can_remote/web/assets/glyphicons-halflings-regular.woff
can_remote/web/assets/glyphicons-halflings-regular.woff2
python_can_remote-0.2.4.dist-info/licenses/LICENSE
python_can_remote-0.2.4.dist-info/METADATA
python_can_remote-0.2.4.dist-info/WHEEL
python_can_remote-0.2.4.dist-info/entry_points.txt
python_can_remote-0.2.4.dist-info/top_level.txt
python_can_remote-0.2.4.dist-info/RECORD
