Metadata-Version: 2.4
Name: python-can-remote
Version: 0.2.4
Summary: CAN over network bridge for Python
Home-page: https://github.com/christiansandberg/python-can-remote
Author: Christian Sandberg
Author-email: christiansandberg@me.com
License: MIT
Keywords: CAN TCP websocket
Platform: any
Classifier: Development Status :: 4 - Beta
Classifier: License :: OSI Approved :: MIT License
Classifier: Operating System :: OS Independent
Classifier: Programming Language :: Python :: 2
Classifier: Programming Language :: Python :: 3
Classifier: Intended Audience :: Developers
Classifier: Topic :: Scientific/Engineering
License-File: LICENSE
Requires-Dist: python-can>=3.0.0
Dynamic: author
Dynamic: author-email
Dynamic: classifier
Dynamic: description
Dynamic: home-page
Dynamic: keywords
Dynamic: license
Dynamic: license-file
Dynamic: platform
Dynamic: requires-dist
Dynamic: summary
